Workbook

Sheet Assumptions
A1: FACTORY INVESTMENT DECISION MODEL — ASSUMPTIONS
A2: Color Legend: | B2: Blue = Input (editable) | C2: Black = Formula
A4: A. INVESTMENT DETAILS
A5: Equipment Purchase Price ($) | B5: 5000000
A6: Installation & Commissioning ($) | B6: 250000
A7: Training & Ramp-Up Cost ($) | B7: 75000
A8: Salvage Value at End of Life ($) | B8: 500000
A9: Asset Useful Life (Years) | B9: 10
A10: Depreciation Method | B10: Straight-Line
A12: B. OPERATIONAL ASSUMPTIONS
A13: Annual Production Capacity (units) | B13: 50000
A14: Target OEE (%) | B14: 0.8
A15: Effective Annual Output (units) | B15: =B13*B14 -> 40000
A16: Selling Price per Unit ($) | B16: 120
A17: Variable Cost per Unit ($) | B17: 55
A18: Annual Fixed Operating Costs ($) | B18: 800000
A19: Annual Maintenance Cost ($) | B19: 120000
A20: Annual Revenue Growth Rate (%) | B20: 0.03
A21: Annual Cost Inflation Rate (%) | B21: 0.02
A23: C. FINANCING & DISCOUNT RATE
A24: Equity Financing (%) | B24: 1
A25: Debt Financing (%) | B25: 0
A26: Cost of Debt (Pre-Tax) (%) | B26: 0.05
A27: Tax Rate (%) | B27: 0.3
A28: Cost of Equity / WACC (%) | B28: 0.1
A30: D. SCENARIO SELECTOR
A31: Active Scenario | B31: Base Case | C31: Options: "Base Case" | "Bull Case" | "Bear Case"
A33: E. SCENARIO ADJUSTMENTS (vs Base Case)
A34: Parameter | B34: Bull Case | C34: Bear Case
A35: OEE Adjustment | B35: +5% | C35: -10%
A36: Price per Unit Adjustment | B36: +$10 | C36: -$15
A37: Revenue Growth Adjustment | B37: +2% | C37: -2%

Sheet DCF Model
A1: FACTORY INVESTMENT DECISION MODEL — 10-YEAR DCF
A3: ($) | B3: Year 1 | C3: Year 2 | D3: Year 3 | E3: Year 4 | F3: Year 5 | G3: Year 6 | H3: Year 7 | I3: Year 8 | J3: Year 9 | K3: Year 10 | L3: Total
A4: REVENUE
A5: Effective Output (units) | B5: =Assumptions!B15 -> 40000 | C5: =B5*(1+Assumptions!$B$21) -> 40800 | D5: =C5*(1+Assumptions!$B$21) -> 41616 | E5: =D5*(1+Assumptions!$B$21) -> 42448.32 | F5: =E5*(1+Assumptions!$B$21) -> 43297.286 | G5: =F5*(1+Assumptions!$B$21) -> 44163.232 | H5: =G5*(1+Assumptions!$B$21) -> 45046.497 | I5: =H5*(1+Assumptions!$B$21) -> 45947.427 | J5: =I5*(1+Assumptions!$B$21) -> 46866.375 | K5: =J5*(1+Assumptions!$B$21) -> 47803.703
A6: Price per Unit ($) | B6: =Assumptions!B16 -> 120 | C6: =B6*(1+Assumptions!$B$21) -> 122.4 | D6: =C6*(1+Assumptions!$B$21) -> 124.848 | E6: =D6*(1+Assumptions!$B$21) -> 127.34496 | F6: =E6*(1+Assumptions!$B$21) -> 129.89186 | G6: =F6*(1+Assumptions!$B$21) -> 132.4897 | H6: =G6*(1+Assumptions!$B$21) -> 135.13949 | I6: =H6*(1+Assumptions!$B$21) -> 137.84228 | J6: =I6*(1+Assumptions!$B$21) -> 140.59913 | K6: =J6*(1+Assumptions!$B$21) -> 143.41111
A7: Gross Revenue ($) | B7: =B5*B6 -> 4800000 | C7: =C5*C6 -> 4993920 | D7: =D5*D6 -> 5195674.4 | E7: =E5*E6 -> 5405579.6 | F7: =F5*F6 -> 5623965 | G7: =G5*G6 -> 5851173.2 | H7: =H5*H6 -> 6087560.6 | I7: =I5*I6 -> 6333498.1 | ... K7: =K5*K6 -> 6855582 | L7: =SUM(B7:K7) -> 57736324
A8: OPERATING COSTS
A9: Variable Costs ($) | B9: =B5*Assumptions!$B$17 -> 2200000 | C9: =C5*Assumptions!$B$17*(1+Assumptions!$B$22)^(2-1) -> 2244000 | D9: =D5*Assumptions!$B$17*(1+Assumptions!$B$22)^(3-1) -> 2288880 | E9: =E5*Assumptions!$B$17*(1+Assumptions!$B$22)^(4-1) -> 2334657.6 | F9: =F5*Assumptions!$B$17*(1+Assumptions!$B$22)^(5-1) -> 2381350.8 | G9: =G5*Assumptions!$B$17*(1+Assumptions!$B$22)^(6-1) -> 2428977.8 | H9: =H5*Assumptions!$B$17*(1+Assumptions!$B$22)^(7-1) -> 2477557.3 | I9: =I5*Assumptions!$B$17*(1+Assumptions!$B$22)^(8-1) -> 2527108.5 | J9: =J5*Assumptions!$B$17*(1+Assumptions!$B$22)^(9-1) -> 2577650.6 | K9: =K5*Assumptions!$B$17*(1+Assumptions!$B$22)^(10-1) -> 2629203.7
A10: Fixed Operating Costs ($) | B10: =Assumptions!$B$18 -> 800000 | C10: =B10*(1+Assumptions!$B$22) -> 800000 | D10: =C10*(1+Assumptions!$B$22) -> 800000 | E10: =D10*(1+Assumptions!$B$22) -> 800000 | F10: =E10*(1+Assumptions!$B$22) -> 800000 | G10: =F10*(1+Assumptions!$B$22) -> 800000 | H10: =G10*(1+Assumptions!$B$22) -> 800000 | I10: =H10*(1+Assumptions!$B$22) -> 800000 | J10: =I10*(1+Assumptions!$B$22) -> 800000 | K10: =J10*(1+Assumptions!$B$22) -> 800000
A11: Maintenance Costs ($) | B11: =Assumptions!$B$19 -> 120000 | C11: =B11*(1+Assumptions!$B$22) -> 120000 | D11: =C11*(1+Assumptions!$B$22) -> 120000 | E11: =D11*(1+Assumptions!$B$22) -> 120000 | F11: =E11*(1+Assumptions!$B$22) -> 120000 | G11: =F11*(1+Assumptions!$B$22) -> 120000 | H11: =G11*(1+Assumptions!$B$22) -> 120000 | I11: =H11*(1+Assumptions!$B$22) -> 120000 | J11: =I11*(1+Assumptions!$B$22) -> 120000 | K11: =J11*(1+Assumptions!$B$22) -> 120000
A12: Depreciation ($) | B12: =(Assumptions!B5+Assumptions!B6+Assumptions!B7-Assumptions!B8)/Assumptions!B9 -> 482500 | C12: =(Assumptions!B5+Assumptions!B6+Assumptions!B7-Assumptions!B8)/Assumptions!B9 -> 482500 | D12: =(Assumptions!B5+Assumptions!B6+Assumptions!B7-Assumptions!B8)/Assumptions!B9 -> 482500 | E12: =(Assumptions!B5+Assumptions!B6+Assumptions!B7-Assumptions!B8)/Assumptions!B9 -> 482500 | F12: =(Assumptions!B5+Assumptions!B6+Assumptions!B7-Assumptions!B8)/Assumptions!B9 -> 482500 | G12: =(Assumptions!B5+Assumptions!B6+Assumptions!B7-Assumptions!B8)/Assumptions!B9 -> 482500 | H12: =(Assumptions!B5+Assumptions!B6+Assumptions!B7-Assumptions!B8)/Assumptions!B9 -> 482500 | I12: =(Assumptions!B5+Assumptions!B6+Assumptions!B7-Assumptions!B8)/Assumptions!B9 -> 482500 | J12: =(Assumptions!B5+Assumptions!B6+Assumptions!B7-Assumptions!B8)/Assumptions!B9 -> 482500 | K12: =(Assumptions!B5+Assumptions!B6+Assumptions!B7-Assumptions!B8)/Assumptions!B9 -> 482500
A13: Total Operating Costs ($) | B13: =SUM(B9:B12) -> 3602500 | C13: =SUM(C9:C12) -> 3646500 | D13: =SUM(D9:D12) -> 3691380 | E13: =SUM(E9:E12) -> 3737157.6 | F13: =SUM(F9:F12) -> 3783850.8 | G13: =SUM(G9:G12) -> 3831477.8 | H13: =SUM(H9:H12) -> 3880057.3 | I13: =SUM(I9:I12) -> 3929608.5 | ... K13: =SUM(K9:K12) -> 4031703.7 | L13: =SUM(B13:K13) -> 38114386
A14: PROFITABILITY
A15: EBIT ($) | B15: =B7-B13 -> 1197500 | C15: =C7-C13 -> 1347420 | D15: =D7-D13 -> 1504294.4 | E15: =E7-E13 -> 1668422 | F15: =F7-F13 -> 1840114.3 | G15: =G7-G13 -> 2019695.4 | H15: =H7-H13 -> 2207503.3 | I15: =I7-I13 -> 2403889.6 | ... K15: =K7-K13 -> 2823878.3 | L15: =SUM(B15:K15) -> 19621938
A16: Taxes ($) | B16: =MAX(B15,0)*Assumptions!$B$27 -> 359250 | C16: =MAX(C15,0)*Assumptions!$B$27 -> 404226 | D16: =MAX(D15,0)*Assumptions!$B$27 -> 451288.31 | E16: =MAX(E15,0)*Assumptions!$B$27 -> 500526.6 | F16: =MAX(F15,0)*Assumptions!$B$27 -> 552034.28 | G16: =MAX(G15,0)*Assumptions!$B$27 -> 605908.63 | H16: =MAX(H15,0)*Assumptions!$B$27 -> 662250.99 | I16: =MAX(I15,0)*Assumptions!$B$27 -> 721166.88 | ... K16: =MAX(K15,0)*Assumptions!$B$27 -> 847163.5
A17: NOPAT ($) | B17: =B15-B16 -> 838250 | C17: =C15-C16 -> 943194 | D17: =D15-D16 -> 1053006.1 | E17: =E15-E16 -> 1167895.4 | F17: =F15-F16 -> 1288080 | G17: =G15-G16 -> 1413786.8 | H17: =H15-H16 -> 1545252.3 | I17: =I15-I16 -> 1682722.7 | ... K17: =K15-K16 -> 1976714.8 | L17: =SUM(B17:K17) -> 13735357
A18: Add Back: Depreciation ($) | B18: =B12 -> 482500 | C18: =C12 -> 482500 | D18: =D12 -> 482500 | E18: =E12 -> 482500 | F18: =F12 -> 482500 | G18: =G12 -> 482500 | H18: =H12 -> 482500 | I18: =I12 -> 482500 | ... K18: =K12 -> 482500
A19: Operating Cash Flow ($) | B19: =B17+B18 -> 1320750 | C19: =C17+C18 -> 1425694 | D19: =D17+D18 -> 1535506.1 | E19: =E17+E18 -> 1650395.4 | F19: =F17+F18 -> 1770580 | G19: =G17+G18 -> 1896286.8 | H19: =H17+H18 -> 2027752.3 | I19: =I17+I18 -> 2165222.7 | ... K19: =K17+K18 -> 2459214.8 | L19: =SUM(B19:K19) -> 18560357
A20: CAPITAL & FREE CASH FLOW
A21: Initial Investment ($) | B21: =-(Assumptions!B5+Assumptions!B6+Assumptions!B7) -> -5325000 | C21: 0 | D21: 0 | E21: 0 | F21: 0 | G21: 0 | H21: 0 | I21: 0 | J21: 0 | K21: 0
A22: Salvage Value ($) | B22: 0 | C22: 0 | D22: 0 | E22: 0 | F22: 0 | G22: 0 | H22: 0 | I22: 0 | J22: 0 | K22: =Assumptions!B8 -> 500000
A23: Free Cash Flow ($) | B23: =B19+B21+B22 -> -4004250 | C23: =C19+C21+C22 -> 1425694 | D23: =D19+D21+D22 -> 1535506.1 | E23: =E19+E21+E22 -> 1650395.4 | F23: =F19+F21+F22 -> 1770580 | G23: =G19+G21+G22 -> 1896286.8 | H23: =H19+H21+H22 -> 2027752.3 | I23: =I19+I21+I22 -> 2165222.7 | ... K23: =K19+K21+K22 -> 2959214.8 | L23: =SUM(B23:K23) -> 13735357
A24: DCF VALUATION
A25: Discount Factor | B25: =1/(1+Assumptions!$B$28)^1 -> 0.90909091 | C25: =1/(1+Assumptions!$B$28)^2 -> 0.82644628 | D25: =1/(1+Assumptions!$B$28)^3 -> 0.7513148 | E25: =1/(1+Assumptions!$B$28)^4 -> 0.68301346 | F25: =1/(1+Assumptions!$B$28)^5 -> 0.62092132 | G25: =1/(1+Assumptions!$B$28)^6 -> 0.56447393 | H25: =1/(1+Assumptions!$B$28)^7 -> 0.51315812 | I25: =1/(1+Assumptions!$B$28)^8 -> 0.46650738 | J25: =1/(1+Assumptions!$B$28)^9 -> 0.42409762 | K25: =1/(1+Assumptions!$B$28)^10 -> 0.38554329
A26: Present Value of FCF ($) | B26: =B23*B25 -> -3640227.3 | C26: =C23*C25 -> 1178259.5 | D26: =D23*D25 -> 1153648.4 | E26: =E23*E25 -> 1127242.3 | F26: =F23*F25 -> 1099390.9 | G26: =G23*G25 -> 1070404.5 | H26: =H23*H25 -> 1040557.6 | I26: =I23*I25 -> 1010092.4 | ... K26: =K23*K25 -> 1140905.4 | L26: =SUM(B26:K26) -> 6159495.7

Sheet Summary & Results
A1: FACTORY INVESTMENT DECISION MODEL — SUMMARY & RESULTS
A3: KEY INVESTMENT METRICS
A4: Metric | B4: Value | C4: Threshold / Benchmark | D4: Decision Signal
A5: Total Initial Investment ($) | B5: =-('DCF Model'!B21) -> 5325000 | C5: — | D5: —
A6: Total Revenue (10 Years) ($) | B6: ='DCF Model'!L7 -> 57736324 | C6: — | D6: —
A7: Total Operating Cash Flow ($) | B7: ='DCF Model'!L19 -> 18560357 | C7: — | D7: —
A8: Net Present Value (NPV) ($) | B8: ='DCF Model'!L26+'DCF Model'!B21 -> 834495.74 | C8: > $0 | D8: =IF(B8>0,"✔ INVEST","✘ REJECT") -> ✔ INVEST
A9: Internal Rate of Return (IRR) (%) | B9: =IFERROR(IRR('DCF Model'!B23:K23),"N/A") -> 0.3986496 | C9: > WACC (10.0%) | D9: =IF(ISNUMBER(B9),IF(B9>Assumptions!B28,"✔ INVEST","✘ REJECT"),"N/A") -> ✔ INVEST
A10: Payback Period (Years) | B10: {=IFERROR(MATCH(TRUE(),MMULT((ROW(INDIRECT("1:10"))>=TRANSPOSE(ROW(INDIRECT("1:10")))),N('DCF Model'!B23:K23))>=ABS('DCF Model'!B21),0),">10")} -> >10 | C10: < 5 Years | D10: =IF(ISNUMBER(B10),IF(B10<5,"✔ INVEST","✘ REVIEW"),"Review") -> Review
A11: EBITDA Margin Year 1 (%) | B11: =('DCF Model'!B15+'DCF Model'!B12)/'DCF Model'!B7 -> 0.35 | C11: > 20% | D11: =IF(B11>0.2,"✔ STRONG","✘ WEAK") -> ✔ STRONG
A12: Return on Investment (%) | B12: ='DCF Model'!L19/ABS('DCF Model'!B21) -> 3.485513 | C12: > 100% | D12: =IF(B12>1,"✔ POSITIVE","✘ NEGATIVE") -> ✔ POSITIVE
A15: SENSITIVITY ANALYSIS — NPV ($) vs OEE & Price per Unit
A16: OEE \ Price/Unit | B16: $90 | C16: $105 | D16: $120 | E16: $135
A17: 65% OEE | B17: {=SUMPRODUCT(((0.65*Assumptions!$B$13*90-0.65*Assumptions!$B$13*Assumptions!$B$17-Assumptions!$B$18-Assumptions!$B$19-(Assumptions!$B$5+Assumptions!$B$6+Assumptions!$B$7-Assumptions!$B$8)/Assumptions!$B$9)*(1-Assumptions!$B$27)+(Assumptions!$B$5+Assumptions!$B$6+Assumptions!$B$7-Assumptions!$B$8)/Assumptions!$B$9)*(1+Assumptions!$B$21)^(ROW(INDIRECT("1:10"))-1)/(1+Assumptions!$B$28)^ROW(INDIRECT("1:10")))-(Assumptions!$B$5+Assumptions!$B$6+Assumptions!$B$7)+Assumptions!$B$8/(1+Assumptions!$B$28)^10} -> -3164511 | C17: {=SUMPRODUCT(((0.65*Assumptions!$B$13*105-0.65*Assumptions!$B$13*Assumptions!$B$17-Assumptions!$B$18-Assumptions!$B$19-(Assumptions!$B$5+Assumptions!$B$6+Assumptions!$B$7-Assumptions!$B$8)/Assumptions!$B$9)*(1-Assumptions!$B$27)+(Assumptions!$B$5+Assumptions!$B$6+Assumptions!$B$7-Assumptions!$B$8)/Assumptions!$B$9)*(1+Assumptions!$B$21)^(ROW(INDIRECT("1:10"))-1)/(1+Assumptions!$B$28)^ROW(INDIRECT("1:10")))-(Assumptions!$B$5+Assumptions!$B$6+Assumptions!$B$7)+Assumptions!$B$8/(1+Assumptions!$B$28)^10} -> -903623.6 | D17: {=SUMPRODUCT(((0.65*Assumptions!$B$13*120-0.65*Assumptions!$B$13*Assumptions!$B$17-Assumptions!$B$18-Assumptions!$B$19-(Assumptions!$B$5+Assumptions!$B$6+Assumptions!$B$7-Assumptions!$B$8)/Assumptions!$B$9)*(1-Assumptions!$B$27)+(Assumptions!$B$5+Assumptions!$B$6+Assumptions!$B$7-Assumptions!$B$8)/Assumptions!$B$9)*(1+Assumptions!$B$21)^(ROW(INDIRECT("1:10"))-1)/(1+Assumptions!$B$28)^ROW(INDIRECT("1:10")))-(Assumptions!$B$5+Assumptions!$B$6+Assumptions!$B$7)+Assumptions!$B$8/(1+Assumptions!$B$28)^10} -> 1357263.8 | E17: {=SUMPRODUCT(((0.65*Assumptions!$B$13*135-0.65*Assumptions!$B$13*Assumptions!$B$17-Assumptions!$B$18-Assumptions!$B$19-(Assumptions!$B$5+Assumptions!$B$6+Assumptions!$B$7-Assumptions!$B$8)/Assumptions!$B$9)*(1-Assumptions!$B$27)+(Assumptions!$B$5+Assumptions!$B$6+Assumptions!$B$7-Assumptions!$B$8)/Assumptions!$B$9)*(1+Assumptions!$B$21)^(ROW(INDIRECT("1:10"))-1)/(1+Assumptions!$B$28)^ROW(INDIRECT("1:10")))-(Assumptions!$B$5+Assumptions!$B$6+Assumptions!$B$7)+Assumptions!$B$8/(1+Assumptions!$B$28)^10} -> 3618151.2
A18: 72% OEE | B18: {=SUMPRODUCT(((0.72*Assumptions!$B$13*90-0.72*Assumptions!$B$13*Assumptions!$B$17-Assumptions!$B$18-Assumptions!$B$19-(Assumptions!$B$5+Assumptions!$B$6+Assumptions!$B$7-Assumptions!$B$8)/Assumptions!$B$9)*(1-Assumptions!$B$27)+(Assumptions!$B$5+Assumptions!$B$6+Assumptions!$B$7-Assumptions!$B$8)/Assumptions!$B$9)*(1+Assumptions!$B$21)^(ROW(INDIRECT("1:10"))-1)/(1+Assumptions!$B$28)^ROW(INDIRECT("1:10")))-(Assumptions!$B$5+Assumptions!$B$6+Assumptions!$B$7)+Assumptions!$B$8/(1+Assumptions!$B$28)^10} -> -2596390.6 | C18: {=SUMPRODUCT(((0.72*Assumptions!$B$13*105-0.72*Assumptions!$B$13*Assumptions!$B$17-Assumptions!$B$18-Assumptions!$B$19-(Assumptions!$B$5+Assumptions!$B$6+Assumptions!$B$7-Assumptions!$B$8)/Assumptions!$B$9)*(1-Assumptions!$B$27)+(Assumptions!$B$5+Assumptions!$B$6+Assumptions!$B$7-Assumptions!$B$8)/Assumptions!$B$9)*(1+Assumptions!$B$21)^(ROW(INDIRECT("1:10"))-1)/(1+Assumptions!$B$28)^ROW(INDIRECT("1:10")))-(Assumptions!$B$5+Assumptions!$B$6+Assumptions!$B$7)+Assumptions!$B$8/(1+Assumptions!$B$28)^10} -> -92022.998 | D18: {=SUMPRODUCT(((0.72*Assumptions!$B$13*120-0.72*Assumptions!$B$13*Assumptions!$B$17-Assumptions!$B$18-Assumptions!$B$19-(Assumptions!$B$5+Assumptions!$B$6+Assumptions!$B$7-Assumptions!$B$8)/Assumptions!$B$9)*(1-Assumptions!$B$27)+(Assumptions!$B$5+Assumptions!$B$6+Assumptions!$B$7-Assumptions!$B$8)/Assumptions!$B$9)*(1+Assumptions!$B$21)^(ROW(INDIRECT("1:10"))-1)/(1+Assumptions!$B$28)^ROW(INDIRECT("1:10")))-(Assumptions!$B$5+Assumptions!$B$6+Assumptions!$B$7)+Assumptions!$B$8/(1+Assumptions!$B$28)^10} -> 2412344.6 | E18: {=SUMPRODUCT(((0.72*Assumptions!$B$13*135-0.72*Assumptions!$B$13*Assumptions!$B$17-Assumptions!$B$18-Assumptions!$B$19-(Assumptions!$B$5+Assumptions!$B$6+Assumptions!$B$7-Assumptions!$B$8)/Assumptions!$B$9)*(1-Assumptions!$B$27)+(Assumptions!$B$5+Assumptions!$B$6+Assumptions!$B$7-Assumptions!$B$8)/Assumptions!$B$9)*(1+Assumptions!$B$21)^(ROW(INDIRECT("1:10"))-1)/(1+Assumptions!$B$28)^ROW(INDIRECT("1:10")))-(Assumptions!$B$5+Assumptions!$B$6+Assumptions!$B$7)+Assumptions!$B$8/(1+Assumptions!$B$28)^10} -> 4916712.1
A19: 80% OEE | B19: {=SUMPRODUCT(((0.8*Assumptions!$B$13*90-0.8*Assumptions!$B$13*Assumptions!$B$17-Assumptions!$B$18-Assumptions!$B$19-(Assumptions!$B$5+Assumptions!$B$6+Assumptions!$B$7-Assumptions!$B$8)/Assumptions!$B$9)*(1-Assumptions!$B$27)+(Assumptions!$B$5+Assumptions!$B$6+Assumptions!$B$7-Assumptions!$B$8)/Assumptions!$B$9)*(1+Assumptions!$B$21)^(ROW(INDIRECT("1:10"))-1)/(1+Assumptions!$B$28)^ROW(INDIRECT("1:10")))-(Assumptions!$B$5+Assumptions!$B$6+Assumptions!$B$7)+Assumptions!$B$8/(1+Assumptions!$B$28)^10} -> -1947110.1 | C19: {=SUMPRODUCT(((0.8*Assumptions!$B$13*105-0.8*Assumptions!$B$13*Assumptions!$B$17-Assumptions!$B$18-Assumptions!$B$19-(Assumptions!$B$5+Assumptions!$B$6+Assumptions!$B$7-Assumptions!$B$8)/Assumptions!$B$9)*(1-Assumptions!$B$27)+(Assumptions!$B$5+Assumptions!$B$6+Assumptions!$B$7-Assumptions!$B$8)/Assumptions!$B$9)*(1+Assumptions!$B$21)^(ROW(INDIRECT("1:10"))-1)/(1+Assumptions!$B$28)^ROW(INDIRECT("1:10")))-(Assumptions!$B$5+Assumptions!$B$6+Assumptions!$B$7)+Assumptions!$B$8/(1+Assumptions!$B$28)^10} -> 835520.55 | D19: {=SUMPRODUCT(((0.8*Assumptions!$B$13*120-0.8*Assumptions!$B$13*Assumptions!$B$17-Assumptions!$B$18-Assumptions!$B$19-(Assumptions!$B$5+Assumptions!$B$6+Assumptions!$B$7-Assumptions!$B$8)/Assumptions!$B$9)*(1-Assumptions!$B$27)+(Assumptions!$B$5+Assumptions!$B$6+Assumptions!$B$7-Assumptions!$B$8)/Assumptions!$B$9)*(1+Assumptions!$B$21)^(ROW(INDIRECT("1:10"))-1)/(1+Assumptions!$B$28)^ROW(INDIRECT("1:10")))-(Assumptions!$B$5+Assumptions!$B$6+Assumptions!$B$7)+Assumptions!$B$8/(1+Assumptions!$B$28)^10} -> 3618151.2 | E19: {=SUMPRODUCT(((0.8*Assumptions!$B$13*135-0.8*Assumptions!$B$13*Assumptions!$B$17-Assumptions!$B$18-Assumptions!$B$19-(Assumptions!$B$5+Assumptions!$B$6+Assumptions!$B$7-Assumptions!$B$8)/Assumptions!$B$9)*(1-Assumptions!$B$27)+(Assumptions!$B$5+Assumptions!$B$6+Assumptions!$B$7-Assumptions!$B$8)/Assumptions!$B$9)*(1+Assumptions!$B$21)^(ROW(INDIRECT("1:10"))-1)/(1+Assumptions!$B$28)^ROW(INDIRECT("1:10")))-(Assumptions!$B$5+Assumptions!$B$6+Assumptions!$B$7)+Assumptions!$B$8/(1+Assumptions!$B$28)^10} -> 6400781.8
A20: 88% OEE | B20: {=SUMPRODUCT(((0.88*Assumptions!$B$13*90-0.88*Assumptions!$B$13*Assumptions!$B$17-Assumptions!$B$18-Assumptions!$B$19-(Assumptions!$B$5+Assumptions!$B$6+Assumptions!$B$7-Assumptions!$B$8)/Assumptions!$B$9)*(1-Assumptions!$B$27)+(Assumptions!$B$5+Assumptions!$B$6+Assumptions!$B$7-Assumptions!$B$8)/Assumptions!$B$9)*(1+Assumptions!$B$21)^(ROW(INDIRECT("1:10"))-1)/(1+Assumptions!$B$28)^ROW(INDIRECT("1:10")))-(Assumptions!$B$5+Assumptions!$B$6+Assumptions!$B$7)+Assumptions!$B$8/(1+Assumptions!$B$28)^10} -> -1297829.6 | C20: {=SUMPRODUCT(((0.88*Assumptions!$B$13*105-0.88*Assumptions!$B$13*Assumptions!$B$17-Assumptions!$B$18-Assumptions!$B$19-(Assumptions!$B$5+Assumptions!$B$6+Assumptions!$B$7-Assumptions!$B$8)/Assumptions!$B$9)*(1-Assumptions!$B$27)+(Assumptions!$B$5+Assumptions!$B$6+Assumptions!$B$7-Assumptions!$B$8)/Assumptions!$B$9)*(1+Assumptions!$B$21)^(ROW(INDIRECT("1:10"))-1)/(1+Assumptions!$B$28)^ROW(INDIRECT("1:10")))-(Assumptions!$B$5+Assumptions!$B$6+Assumptions!$B$7)+Assumptions!$B$8/(1+Assumptions!$B$28)^10} -> 1763064.1 | D20: {=SUMPRODUCT(((0.88*Assumptions!$B$13*120-0.88*Assumptions!$B$13*Assumptions!$B$17-Assumptions!$B$18-Assumptions!$B$19-(Assumptions!$B$5+Assumptions!$B$6+Assumptions!$B$7-Assumptions!$B$8)/Assumptions!$B$9)*(1-Assumptions!$B$27)+(Assumptions!$B$5+Assumptions!$B$6+Assumptions!$B$7-Assumptions!$B$8)/Assumptions!$B$9)*(1+Assumptions!$B$21)^(ROW(INDIRECT("1:10"))-1)/(1+Assumptions!$B$28)^ROW(INDIRECT("1:10")))-(Assumptions!$B$5+Assumptions!$B$6+Assumptions!$B$7)+Assumptions!$B$8/(1+Assumptions!$B$28)^10} -> 4823957.8 | E20: {=SUMPRODUCT(((0.88*Assumptions!$B$13*135-0.88*Assumptions!$B$13*Assumptions!$B$17-Assumptions!$B$18-Assumptions!$B$19-(Assumptions!$B$5+Assumptions!$B$6+Assumptions!$B$7-Assumptions!$B$8)/Assumptions!$B$9)*(1-Assumptions!$B$27)+(Assumptions!$B$5+Assumptions!$B$6+Assumptions!$B$7-Assumptions!$B$8)/Assumptions!$B$9)*(1+Assumptions!$B$21)^(ROW(INDIRECT("1:10"))-1)/(1+Assumptions!$B$28)^ROW(INDIRECT("1:10")))-(Assumptions!$B$5+Assumptions!$B$6+Assumptions!$B$7)+Assumptions!$B$8/(1+Assumptions!$B$28)^10} -> 7884851.5
A21: 95% OEE | B21: {=SUMPRODUCT(((0.95*Assumptions!$B$13*90-0.95*Assumptions!$B$13*Assumptions!$B$17-Assumptions!$B$18-Assumptions!$B$19-(Assumptions!$B$5+Assumptions!$B$6+Assumptions!$B$7-Assumptions!$B$8)/Assumptions!$B$9)*(1-Assumptions!$B$27)+(Assumptions!$B$5+Assumptions!$B$6+Assumptions!$B$7-Assumptions!$B$8)/Assumptions!$B$9)*(1+Assumptions!$B$21)^(ROW(INDIRECT("1:10"))-1)/(1+Assumptions!$B$28)^ROW(INDIRECT("1:10")))-(Assumptions!$B$5+Assumptions!$B$6+Assumptions!$B$7)+Assumptions!$B$8/(1+Assumptions!$B$28)^10} -> -729709.18 | C21: {=SUMPRODUCT(((0.95*Assumptions!$B$13*105-0.95*Assumptions!$B$13*Assumptions!$B$17-Assumptions!$B$18-Assumptions!$B$19-(Assumptions!$B$5+Assumptions!$B$6+Assumptions!$B$7-Assumptions!$B$8)/Assumptions!$B$9)*(1-Assumptions!$B$27)+(Assumptions!$B$5+Assumptions!$B$6+Assumptions!$B$7-Assumptions!$B$8)/Assumptions!$B$9)*(1+Assumptions!$B$21)^(ROW(INDIRECT("1:10"))-1)/(1+Assumptions!$B$28)^ROW(INDIRECT("1:10")))-(Assumptions!$B$5+Assumptions!$B$6+Assumptions!$B$7)+Assumptions!$B$8/(1+Assumptions!$B$28)^10} -> 2574664.7 | D21: {=SUMPRODUCT(((0.95*Assumptions!$B$13*120-0.95*Assumptions!$B$13*Assumptions!$B$17-Assumptions!$B$18-Assumptions!$B$19-(Assumptions!$B$5+Assumptions!$B$6+Assumptions!$B$7-Assumptions!$B$8)/Assumptions!$B$9)*(1-Assumptions!$B$27)+(Assumptions!$B$5+Assumptions!$B$6+Assumptions!$B$7-Assumptions!$B$8)/Assumptions!$B$9)*(1+Assumptions!$B$21)^(ROW(INDIRECT("1:10"))-1)/(1+Assumptions!$B$28)^ROW(INDIRECT("1:10")))-(Assumptions!$B$5+Assumptions!$B$6+Assumptions!$B$7)+Assumptions!$B$8/(1+Assumptions!$B$28)^10} -> 5879038.6 | E21: {=SUMPRODUCT(((0.95*Assumptions!$B$13*135-0.95*Assumptions!$B$13*Assumptions!$B$17-Assumptions!$B$18-Assumptions!$B$19-(Assumptions!$B$5+Assumptions!$B$6+Assumptions!$B$7-Assumptions!$B$8)/Assumptions!$B$9)*(1-Assumptions!$B$27)+(Assumptions!$B$5+Assumptions!$B$6+Assumptions!$B$7-Assumptions!$B$8)/Assumptions!$B$9)*(1+Assumptions!$B$21)^(ROW(INDIRECT("1:10"))-1)/(1+Assumptions!$B$28)^ROW(INDIRECT("1:10")))-(Assumptions!$B$5+Assumptions!$B$6+Assumptions!$B$7)+Assumptions!$B$8/(1+Assumptions!$B$28)^10} -> 9183412.4
A24: INVESTMENT RECOMMENDATION
A25: Decision: | B25: =IF(B8>0,IF(B9>Assumptions!B28,"PROCEED WITH INVESTMENT","REVIEW — IRR BELOW HURDLE"),"DO NOT INVEST — NEGATIVE NPV") -> PROCEED WITH INVESTMENT
A26: NPV Status: | B26: =IF(B8>0,"Project creates value above the cost of capital.","Project destroys value. Revisit assumptions.") -> Project creates value above the cost of capital.

Sheet Scenario Comparison
A1: FACTORY INVESTMENT DECISION MODEL — SCENARIO COMPARISON
A3: SCENARIO ASSUMPTIONS
A4: Parameter | B4: Bear Case | C4: Base Case | D4: Bull Case
A5: OEE (%) | B5: =Assumptions!B14-0.1 -> 0.7 | C5: =Assumptions!B14 -> 0.8 | D5: =Assumptions!B14+0.05 -> 0.85
A6: Price per Unit ($) | B6: =Assumptions!B16-15 -> 105 | C6: =Assumptions!B16 -> 120 | D6: =Assumptions!B16+10 -> 130
A7: Revenue Growth Rate (%) | B7: =Assumptions!B21-0.02 -> 0 | C7: =Assumptions!B21 -> 0.02 | D7: =Assumptions!B21+0.02 -> 0.04
A8: Variable Cost per Unit ($) | B8: =Assumptions!B17 -> 55 | C8: =Assumptions!B17 -> 55 | D8: =Assumptions!B17 -> 55
A9: WACC (%) | B9: =Assumptions!B28 -> 0.1 | C9: =Assumptions!B28 -> 0.1 | D9: =Assumptions!B28 -> 0.1
A11: SCENARIO RESULTS
A12: Metric | B12: Bear Case | C12: Base Case | D12: Bull Case
A13: NPV ($) | B13: {=SUMPRODUCT(((B5*Assumptions!$B$13*B6-B5*Assumptions!$B$13*Assumptions!$B$17-Assumptions!$B$18-Assumptions!$B$19-(Assumptions!$B$5+Assumptions!$B$6+Assumptions!$B$7-Assumptions!$B$8)/Assumptions!$B$9)*(1-Assumptions!$B$27)+(Assumptions!$B$5+Assumptions!$B$6+Assumptions!$B$7-Assumptions!$B$8)/Assumptions!$B$9)*(1+B7)^(ROW(INDIRECT("1:10"))-1)/(1+Assumptions!$B$28)^ROW(INDIRECT("1:10")))-(Assumptions!$B$5+Assumptions!$B$6+Assumptions!$B$7)+Assumptions!$B$8/(1+Assumptions!$B$28)^10} -> -672808.78 | C13: {=SUMPRODUCT(((C5*Assumptions!$B$13*C6-C5*Assumptions!$B$13*Assumptions!$B$17-Assumptions!$B$18-Assumptions!$B$19-(Assumptions!$B$5+Assumptions!$B$6+Assumptions!$B$7-Assumptions!$B$8)/Assumptions!$B$9)*(1-Assumptions!$B$27)+(Assumptions!$B$5+Assumptions!$B$6+Assumptions!$B$7-Assumptions!$B$8)/Assumptions!$B$9)*(1+C7)^(ROW(INDIRECT("1:10"))-1)/(1+Assumptions!$B$28)^ROW(INDIRECT("1:10")))-(Assumptions!$B$5+Assumptions!$B$6+Assumptions!$B$7)+Assumptions!$B$8/(1+Assumptions!$B$28)^10} -> 3618151.2 | D13: {=SUMPRODUCT(((D5*Assumptions!$B$13*D6-D5*Assumptions!$B$13*Assumptions!$B$17-Assumptions!$B$18-Assumptions!$B$19-(Assumptions!$B$5+Assumptions!$B$6+Assumptions!$B$7-Assumptions!$B$8)/Assumptions!$B$9)*(1-Assumptions!$B$27)+(Assumptions!$B$5+Assumptions!$B$6+Assumptions!$B$7-Assumptions!$B$8)/Assumptions!$B$9)*(1+D7)^(ROW(INDIRECT("1:10"))-1)/(1+Assumptions!$B$28)^ROW(INDIRECT("1:10")))-(Assumptions!$B$5+Assumptions!$B$6+Assumptions!$B$7)+Assumptions!$B$8/(1+Assumptions!$B$28)^10} -> 7260282.1
A14: Approx. IRR (%) | B14: =(B13+(Assumptions!$B$5+Assumptions!$B$6+Assumptions!$B$7))/(Assumptions!$B$5+Assumptions!$B$6+Assumptions!$B$7)/Assumptions!$B$9 -> 0.087365093 | C14: =(C13+(Assumptions!$B$5+Assumptions!$B$6+Assumptions!$B$7))/(Assumptions!$B$5+Assumptions!$B$6+Assumptions!$B$7)/Assumptions!$B$9 -> 0.1679465 | D14: =(D13+(Assumptions!$B$5+Assumptions!$B$6+Assumptions!$B$7))/(Assumptions!$B$5+Assumptions!$B$6+Assumptions!$B$7)/Assumptions!$B$9 -> 0.23634333
A15: Year 1 Revenue ($) | B15: =B5*Assumptions!$B$13*B6 -> 3675000 | C15: =C5*Assumptions!$B$13*C6 -> 4800000 | D15: =D5*Assumptions!$B$13*D6 -> 5525000
A16: Year 1 EBITDA ($) | B16: =B5*Assumptions!$B$13*(B6-Assumptions!$B$17)-Assumptions!$B$18-Assumptions!$B$19 -> 830000 | C16: =C5*Assumptions!$B$13*(C6-Assumptions!$B$17)-Assumptions!$B$18-Assumptions!$B$19 -> 1680000 | D16: =D5*Assumptions!$B$13*(D6-Assumptions!$B$17)-Assumptions!$B$18-Assumptions!$B$19 -> 2267500
A17: Year 1 EBITDA Margin (%) | B17: =B16/B15 -> 0.22585034 | C17: =C16/C15 -> 0.35 | D17: =D16/D15 -> 0.41040724
A19: Recommendation | B19: =IF(B13>0,"✔ INVEST","✘ REJECT") -> ✘ REJECT | C19: =IF(C13>0,"✔ INVEST","✘ REJECT") -> ✔ INVEST | D19: =IF(D13>0,"✔ INVEST","✘ REJECT") -> ✔ INVEST
